aquiche/__init__.py
aquiche/_alru_cache.py
aquiche/_async_cache.py
aquiche/_cache_params.py
aquiche/_core.py
aquiche/_expiration.py
aquiche/_hash.py
aquiche/_registry.py
aquiche/_repository.py
aquiche/_sync_cache.py
aquiche/errors.py
aquiche/utils/__init__.py
aquiche/utils/_async_utils.py
aquiche/utils/_extraction_utils.py
aquiche/utils/_scanner.py
aquiche/utils/_singleton.py
aquiche/utils/_sum_expression_parser.py
aquiche/utils/_time_parse.py
aquiche-1.3.1.dist-info/entry_points.txt
aquiche-1.3.1.dist-info/LICENSE
aquiche-1.3.1.dist-info/WHEEL
aquiche-1.3.1.dist-info/METADATA
aquiche-1.3.1.dist-info/RECORD
