Metadata-Version: 2.1
Name: aquiche
Version: 1.3.1
Summary: Async cache in-memory
License: MIT
Author: Jakub Jantosik
Author-email: jakub.jantosik@gmail.com
Requires-Python: >=3.8,<4.0
Classifier: License :: OSI Approved :: MIT License
Classifier: Programming Language :: Python :: 3
Classifier: Programming Language :: Python :: 3.8
Classifier: Programming Language :: Python :: 3.9
Classifier: Programming Language :: Python :: 3.10
Classifier: Programming Language :: Python :: 3.11
Requires-Dist: typing-extensions (>=4.4,<5.0); python_version < "3.10"
